sorti.py
sorti-2.0.1.dist-info/LICENSE
sorti-2.0.1.dist-info/METADATA
sorti-2.0.1.dist-info/WHEEL
sorti-2.0.1.dist-info/entry_points.txt
sorti-2.0.1.dist-info/top_level.txt
sorti-2.0.1.dist-info/RECORD
