Metadata-Version: 2.1
Name: sorti
Version: 2.0.1
Summary: An opinionated CLI for asottile/reorder_python_imports
Home-page: https://github.com/antonagestam/sorti
Author: Anton Agestam
Author-email: git@antonagestam.se
License: MIT
Platform: UNKNOWN
Classifier: License :: OSI Approved :: MIT License
Classifier: Programming Language :: Python :: 3.7
Requires-Python: >=3.7
Requires-Dist: reorder-python-imports (>=1.5.0)
Requires-Dist: black (>=19.3b0)
